kheops_client/__init__.py
kheops_client/__main__.py
kheops_client/_client.py
kheops_client/_utils.py
kheops_client-0.3.1.dist-info/LICENSE
kheops_client-0.3.1.dist-info/METADATA
kheops_client-0.3.1.dist-info/WHEEL
kheops_client-0.3.1.dist-info/entry_points.txt
kheops_client-0.3.1.dist-info/top_level.txt
kheops_client-0.3.1.dist-info/RECORD
