Metadata-Version: 2.1
Name: kheops-client
Version: 0.3.1
Summary: Utility for querying and downloading data from a Kheops DICOM database
Home-page: https://github.com/hirsch-lab/kheops-client
Author: Norman Juchler
License: MIT
Keywords: kheops,client,dicom,DICOMWeb
Classifier: Programming Language :: Python :: 3
Classifier: License :: OSI Approved :: MIT License
Classifier: Operating System :: OS Independent
Classifier: Topic :: Database
Classifier: Topic :: Internet
Classifier: Topic :: Utilities
Classifier: Intended Audience :: Developers
Classifier: Intended Audience :: Science/Research
Classifier: Topic :: Scientific/Engineering :: Medical Science Apps.
Requires-Python: >=3.6
License-File: LICENSE
Requires-Dist: pandas (>=1.1)
Requires-Dist: pydicom (>=2.1)
Requires-Dist: dicomweb-client (>=0.52)
Requires-Dist: progressbar2
